docman/__init__.py
docman/__main__.py
docman/console.py
docman/filemanager.py
docman-0.0.6.dist-info/LICENSE.txt
docman-0.0.6.dist-info/METADATA
docman-0.0.6.dist-info/WHEEL
docman-0.0.6.dist-info/entry_points.txt
docman-0.0.6.dist-info/top_level.txt
docman-0.0.6.dist-info/RECORD
