Metadata-Version: 2.1
Name: docman
Version: 0.0.6
Summary: Document Manager
Author-email: David <c0d3@gpobox.net>
Maintainer-email: David <c0d3@gpobox.net>
License: Copyright © 2024 David <c0d3@gpobox.net>
Project-URL: Homepage, https://github.com/bbc6502/docman
Project-URL: Bug Tracker, https://github.com/bbc6502/docman/issues
Keywords: documents
Classifier: Programming Language :: Python :: 3
Classifier: License :: OSI Approved :: MIT License
Classifier: Operating System :: OS Independent
Classifier: Development Status :: 3 - Alpha
Classifier: Natural Language :: English
Classifier: Operating System :: POSIX :: Linux
Classifier: Topic :: Utilities
Requires-Python: >=3.11
License-File: LICENSE.txt
Provides-Extra: dev
Requires-Dist: wheel; extra == "dev"
Requires-Dist: build; extra == "dev"
Requires-Dist: twine; extra == "dev"
Provides-Extra: test
Requires-Dist: pytest; extra == "test"
Requires-Dist: pytest-cov; extra == "test"
Requires-Dist: coverage; extra == "test"
